odoo/addons/procurement_purchase_requisition_generation/README.rst
odoo/addons/procurement_purchase_requisition_generation/__init__.py
odoo/addons/procurement_purchase_requisition_generation/__manifest__.py
odoo/addons/procurement_purchase_requisition_generation/i18n/es.po
odoo/addons/procurement_purchase_requisition_generation/i18n/it.po
odoo/addons/procurement_purchase_requisition_generation/i18n/procurement_purchase_requisition_generation.pot
odoo/addons/procurement_purchase_requisition_generation/models/__init__.py
odoo/addons/procurement_purchase_requisition_generation/models/product_template.py
odoo/addons/procurement_purchase_requisition_generation/models/purchase_requisition.py
odoo/addons/procurement_purchase_requisition_generation/models/stock_rule.py
odoo/addons/procurement_purchase_requisition_generation/readme/CONFIGURE.md
odoo/addons/procurement_purchase_requisition_generation/readme/CONTEXT.md
odoo/addons/procurement_purchase_requisition_generation/readme/CONTRIBUTORS.md
odoo/addons/procurement_purchase_requisition_generation/readme/DESCRIPTION.md
odoo/addons/procurement_purchase_requisition_generation/readme/USAGE.md
odoo/addons/procurement_purchase_requisition_generation/static/description/icon.png
odoo/addons/procurement_purchase_requisition_generation/static/description/index.html
odoo/addons/procurement_purchase_requisition_generation/tests/__init__.py
odoo/addons/procurement_purchase_requisition_generation/tests/test_procurement_purchase_requisition_generation.py
odoo/addons/procurement_purchase_requisition_generation/views/product_template_views.xml
odoo/addons/procurement_purchase_requisition_generation/views/purchase_requisition_views.xml
odoo/addons/procurement_purchase_requisition_generation/wizards/__init__.py
odoo/addons/procurement_purchase_requisition_generation/wizards/product_replenish.py
odoo_addon_procurement_purchase_requisition_generation-17.0.1.0.0.7.dist-info/METADATA
odoo_addon_procurement_purchase_requisition_generation-17.0.1.0.0.7.dist-info/WHEEL
odoo_addon_procurement_purchase_requisition_generation-17.0.1.0.0.7.dist-info/top_level.txt
odoo_addon_procurement_purchase_requisition_generation-17.0.1.0.0.7.dist-info/RECORD
